[{"niveau":3,"quiz":"oui","prononciation":"いち","kanji":"一","hint":"easy!"},
{"niveau":3,"quiz":"oui","prononciation":"に","kanji":"二","hint":"easy!"},
{"niveau":3,"quiz":"oui","prononciation":"さん","kanji":"三","hint":"easy!"},
{"niveau":3,"quiz":"oui","prononciation":"ご","kanji":"五","hint":"easy!"},
{"niveau":3,"quiz":"oui","prononciation":"ろく","kanji":"六","hint":"easy!"},
{"niveau":3,"quiz":"oui","prononciation":"しち","kanji":"七","hint":"easy!"},
{"niveau":3,"quiz":"oui","prononciation":"なな","kanji":"七","hint":"easy!"},
{"niveau":3,"quiz":"oui","prononciation":"はち","kanji":"八","hint":"easy!"},
{"niveau":3,"quiz":"oui","prononciation":"はっぴゃく","kanji":"八百","hint":"easy!"},
{"niveau":3,"quiz":"oui","prononciation":"きゅう","kanji":"九","hint":"easy!"},
{"niveau":3,"quiz":"oui","prononciation":"じゅう","kanji":"十","hint":"easy!"},
{"niveau":3,"quiz":"oui","prononciation":"ひゃく","kanji":"百","hint":"easy!"},
{"niveau":3,"quiz":"oui","prononciation":"せん","kanji":"千","hint":"easy!"},
{"niveau":3,"quiz":"oui","prononciation":"まん","kanji":"万","hint":"easy!"},
{"niveau":3,"quiz":"oui","prononciation":"えん","kanji":"円","hint":"easy!"},
{"niveau":3,"quiz":"oui","prononciation":"じ","kanji":"時","hint":"easy!"},
{"niveau":4,"quiz":"non","prononciation":"おかね","kanji":"お金","hint":"easy!"},
{"niveau":4,"quiz":"non","prononciation":"やまもとさん","kanji":"山本さん","hint":"easy!"},
{"niveau":4,"quiz":"non","prononciation":"つき","kanji":"月","hint":"easy!"},
{"niveau":4,"quiz":"non","prononciation":"ひ","kanji":"火","hint":"fire"},
{"niveau":4,"quiz":"non","prononciation":"き","kanji":"木","hint":"tree"},
{"niveau":4,"quiz":"non","prononciation":"ひと","kanji":"人","hint":"easy!"},
{"niveau":4,"quiz":"oui","prononciation":"にほん","kanji":"日本","hint":"easy!"},
{"niveau":4,"quiz":"oui","prononciation":"にちようび","kanji":"日曜日","hint":"easy!"},
{"niveau":4,"quiz":"oui","prononciation":"ほん","kanji":"本","hint":"easy!"},
{"niveau":4,"quiz":"oui","prononciation":"にほんじん","kanji":"日本人","hint":"easy!"},
{"niveau":4,"quiz":"oui","prononciation":"ひとりで","kanji":"一人で","hint":"easy!"},
{"niveau":4,"quiz":"oui","prononciation":"げつようび","kanji":"月曜日","hint":"easy!"},
{"niveau":4,"quiz":"oui","prononciation":"いちがつ","kanji":"一月","hint":"easy!"},
{"niveau":4,"quiz":"oui","prononciation":"かようび","kanji":"火曜日","hint":"easy!"},
{"niveau":4,"quiz":"oui","prononciation":"すいようび","kanji":"水曜日","hint":"easy!"},
{"niveau":4,"quiz":"oui","prononciation":"みず","kanji":"水","hint":"easy!"},
{"niveau":4,"quiz":"oui","prononciation":"もくようび","kanji":"木曜日","hint":"easy!"},
{"niveau":4,"quiz":"oui","prononciation":"きんようび","kanji":"金曜日","hint":"easy!"},
{"niveau":4,"quiz":"oui","prononciation":"どようび","kanji":"土曜日","hint":"easy!"},
{"niveau":4,"quiz":"oui","prononciation":"うえ","kanji":"上","hint":"easy!"},
{"niveau":4,"quiz":"oui","prononciation":"した","kanji":"下","hint":"easy!"},
{"niveau":4,"quiz":"oui","prononciation":"なか","kanji":"中","hint":"easy!"},
{"niveau":4,"quiz":"oui","prononciation":"さんじはん","kanji":"三時半","hint":"easy!"},
{"niveau":5,"quiz":"non","prononciation":"こんばん","kanji":"今晩","hint":"evening (hi)"},
{"niveau":5,"quiz":"non","prononciation":"たべもの","kanji":"食べ物","hint":"mono: 物"},
{"niveau":5,"quiz":"non","prononciation":"のみもの","kanji":"飲み物","hint":"mono: 物"},
{"niveau":5,"quiz":"non","prononciation":"でんき","kanji":"電気","hint":"electricity"},
{"niveau":5,"quiz":"non","prononciation":"てんごく","kanji":"天国","hint":"heaven"},
{"niveau":5,"quiz":"oui","prononciation":"たなかさん","kanji":"田中さん","hint":"easy!"},
{"niveau":5,"quiz":"oui","prononciation":"やまださん","kanji":"山田さん","hint":"easy!"},
{"niveau":5,"quiz":"oui","prononciation":"おんなのひと","kanji":"女の人","hint":"easy!"},
{"niveau":5,"quiz":"oui","prononciation":"おとこのひと","kanji":"男の人","hint":"easy!"},
{"niveau":5,"quiz":"oui","prononciation":"みる","kanji":"見る","hint":"easy!"},
{"niveau":5,"quiz":"oui","prononciation":"いく","kanji":"行く","hint":"easy!"},
{"niveau":5,"quiz":"oui","prononciation":"たべる","kanji":"食べる","hint":"easy!"},
{"niveau":5,"quiz":"oui","prononciation":"のむ","kanji":"飲む","hint":"easy!"},
{"niveau":5,"quiz":"oui","prononciation":"げんき","kanji":"元気","hint":"easy!...energy"},
{"niveau":5,"quiz":"oui","prononciation":"わたし","kanji":"私","hint":"easy!...I"},
{"niveau":5,"quiz":"oui","prononciation":"やま","kanji":"山","hint":"easy!...mountain"},
{"niveau":5,"quiz":"oui","prononciation":"いま","kanji":"今","hint":"easy!...now"},
{"niveau":5,"quiz":"oui","prononciation":"かわ","kanji":"川","hint":"easy!...river"},
{"niveau":5,"quiz":"oui","prononciation":"てんき","kanji":"天気","hint":"weather"},
{"niveau":6,"quiz":"non","prononciation":"だす","kanji":"出す","hint":"easy!"},
{"niveau":6,"quiz":"non","prononciation":"せんしゅう","kanji":"先週","hint":"last week (週）"},
{"niveau":6,"quiz":"non","prononciation":"くち","kanji":"口","hint":"mouth"},
{"niveau":6,"quiz":"non","prononciation":"がっこう","kanji":"学校","hint":"school"},
{"niveau":6,"quiz":"non","prononciation":"うまれる","kanji":"生まれる","hint":"to be born"},
{"niveau":6,"quiz":"non","prononciation":"おとな","kanji":"大人","hint":"adult"},
{"niveau":6,"quiz":"non","prononciation":"さきに","kanji":"先に","hint":"ahead"},
{"niveau":6,"quiz":"non","prononciation":"くに","kanji":"国","hint":"country"},
{"niveau":6,"quiz":"non","prononciation":"とうきょう","kanji":"東京","hint":"east capital"},
{"niveau":6,"quiz":"non","prononciation":"ほくせい","kanji":"北西","hint":"northwest"},
{"niveau":6,"quiz":"non","prononciation":"じぶん","kanji":"自分","hint":"oneself"},
{"niveau":6,"quiz":"non","prononciation":"そと","kanji":"外","hint":"outside"},
{"niveau":6,"quiz":"non","prononciation":"じんこう","kanji":"人口","hint":"population"},
{"niveau":6,"quiz":"non","prononciation":"なんとう","kanji":"南東","hint":"southeast"},
{"niveau":6,"quiz":"oui","prononciation":"みぎ","kanji":"右","hint":"easy!"},
{"niveau":6,"quiz":"oui","prononciation":"ひだり","kanji":"左","hint":"easy!"},
{"niveau":6,"quiz":"oui","prononciation":"じゅっぷん","kanji":"十分","hint":"easy!"},
{"niveau":6,"quiz":"oui","prononciation":"せんせい","kanji":"先生","hint":"easy!"},
{"niveau":6,"quiz":"oui","prononciation":"がくせい","kanji":"学生","hint":"easy!"},
{"niveau":6,"quiz":"oui","prononciation":"だいがくせい","kanji":"大学生","hint":"easy!"},
{"niveau":6,"quiz":"oui","prononciation":"おおきい","kanji":"大きい","hint":"easy!"},
{"niveau":6,"quiz":"oui","prononciation":"ちゅうごく","kanji":"中国","hint":"easy!"},
{"niveau":6,"quiz":"oui","prononciation":"ひがし","kanji":"東","hint":"east"},
{"niveau":6,"quiz":"oui","prononciation":"ひがしぐち","kanji":"東口","hint":"east exit"},
{"niveau":6,"quiz":"oui","prononciation":"でる","kanji":"出る","hint":"easy!"},
{"niveau":6,"quiz":"oui","prononciation":"でぐち","kanji":"出口","hint":"exit"},
{"niveau":6,"quiz":"oui","prononciation":"ごふん","kanji":"五分","hint":"five minutes"},
{"niveau":6,"quiz":"oui","prononciation":"がいこくじん","kanji":"外国人","hint":"foreigner"},
{"niveau":6,"quiz":"oui","prononciation":"きた","kanji":"北","hint":"north"},
{"niveau":6,"quiz":"oui","prononciation":"きたぐち","kanji":"北口","hint":"north exit"},
{"niveau":6,"quiz":"oui","prononciation":"みなみ","kanji":"南","hint":"south"},
{"niveau":6,"quiz":"oui","prononciation":"みなみぐち","kanji":"南口","hint":"south exit"},
{"niveau":6,"quiz":"oui","prononciation":"にし","kanji":"西","hint":"west"},
{"niveau":6,"quiz":"oui","prononciation":"にしぐち","kanji":"西口","hint":"west exit"},
{"niveau":7,"quiz":"non","prononciation":"ぼご","kanji":"母語","hint":"mother tongue"},
{"niveau":7,"quiz":"non","prononciation":"きょうと","kanji":"京と","hint":"capital"},
{"niveau":7,"quiz":"non","prononciation":"しょうがっこう","kanji":"小学校","hint":"elementary school"},
{"niveau":7,"quiz":"non","prononciation":" しょうがくせい","kanji":"小学生","hint":"elementary school student"},
{"niveau":7,"quiz":"non","prononciation":"いりぐち","kanji":"入口","hint":"entrance"},
{"niveau":7,"quiz":"non","prononciation":"きこく","kanji":"帰国","hint":"going home"},
{"niveau":7,"quiz":"non","prononciation":"かいしゃいん","kanji":"会社員","hint":"office worker"},
{"niveau":7,"quiz":"non","prononciation":"いれる","kanji":"入れる","hint":"to put something in"},
{"niveau":7,"quiz":"oui","prononciation":"がっこう","kanji":"学校","hint":"school"},
{"niveau":7,"quiz":"oui","prononciation":"ちいさい","kanji":"小さい","hint":"small"},
{"niveau":7,"quiz":"oui","prononciation":"きょうこ","kanji":"京子","hint":"capital child"},
{"niveau":7,"quiz":"oui","prononciation":"かいしゃ","kanji":"会社","hint":"company"},
{"niveau":7,"quiz":"oui","prononciation":"とうきょう","kanji":"東京","hint":"east capital"},
{"niveau":7,"quiz":"oui","prononciation":"ちち","kanji":"父","hint":"easy!"},
{"niveau":7,"quiz":"oui","prononciation":"おとうさん","kanji":"お父さん","hint":"easy!"},
{"niveau":7,"quiz":"oui","prononciation":"はは","kanji":"母","hint":"easy!"},
{"niveau":7,"quiz":"oui","prononciation":"おかあさん","kanji":"お母さん","hint":"easy!"},
{"niveau":7,"quiz":"oui","prononciation":"たかい","kanji":"高い","hint":"easy!"},
{"niveau":7,"quiz":"oui","prononciation":"まいにち","kanji":"毎日","hint":"easy!"},
{"niveau":7,"quiz":"oui","prononciation":"にほんご","kanji":"日本語","hint":"easy!"},
{"niveau":7,"quiz":"oui","prononciation":"こうこうせい","kanji":"高校生","hint":"high school student"},
{"niveau":7,"quiz":"oui","prononciation":"ぶんがく","kanji":"文学","hint":"literature"},
{"niveau":7,"quiz":"oui","prononciation":"あう","kanji":"会う","hint":"to meet"},
{"niveau":7,"quiz":"oui","prononciation":"かえる","kanji":"帰る","hint":"う-verb"},
{"niveau":7,"quiz":"oui","prononciation":"はいる","kanji":"入る","hint":"う-verb"},
{"niveau":7,"quiz":"oui","prononciation":"こども","kanji":"子供","hint":"juste こ"},
{"niveau":8,"quiz":"non","prononciation":"きゅうじつ","kanji":"休日","hint":"holiday"},
{"niveau":8,"quiz":"non","prononciation":"げんごがく","kanji":"言語学","hint":"linguistics"},
{"niveau":8,"quiz":"non","prononciation":"しょくじ","kanji":"食事","hint":"meal"},
{"niveau":8,"quiz":"non","prononciation":"どくしょ","kanji":"読書","hint":"reading books"},
{"niveau":8,"quiz":"non","prononciation":"じじょ","kanji":"次女","hint":"second daughter"},
{"niveau":8,"quiz":"non","prononciation":"てんいん","kanji":"店員","hint":"store clerk"},
{"niveau":8,"quiz":"non","prononciation":"でんわ","kanji":"電話","hint":"telephone"},
{"niveau":8,"quiz":"non","prononciation":"かじ","kanji":"火事","hint":"fire"},
{"niveau":8,"quiz":"non","prononciation":"こと","kanji":"事","hint":"thing"},
{"niveau":8,"quiz":"non","prononciation":"さくぶん","kanji":"作文","hint":"to make sentence"},
{"niveau":8,"quiz":"oui","prononciation":"やすみ","kanji":"休み","hint":"holiday, absence"},
{"niveau":8,"quiz":"oui","prononciation":"しごと","kanji":"仕事","hint":"job"},
{"niveau":8,"quiz":"oui","prononciation":"あたらしい","kanji":"新しい","hint":"new"},
{"niveau":8,"quiz":"oui","prononciation":"くるま","kanji":"車","hint":"easy!"},
{"niveau":8,"quiz":"oui","prononciation":"なに","kanji":"何","hint":"easy!"},
{"niveau":8,"quiz":"oui","prononciation":"なんじ","kanji":"何時","hint":"easy!"},
{"niveau":8,"quiz":"oui","prononciation":"なんにん","kanji":"何人","hint":"easy!"},
{"niveau":8,"quiz":"oui","prononciation":"でんき","kanji":"電気","hint":"electricity (see level 3)"},
{"niveau":8,"quiz":"oui","prononciation":"しんぶん","kanji":"新聞","hint":"newspaper"},
{"niveau":8,"quiz":"oui","prononciation":"つぎ","kanji":"次","hint":"next"},
{"niveau":8,"quiz":"oui","prononciation":"きく","kanji":"聞く","hint":"to listen"},
{"niveau":8,"quiz":"oui","prononciation":"よむ","kanji":"読む","hint":"to read"},
{"niveau":8,"quiz":"oui","prononciation":"やすむ","kanji":"休む","hint":"to rest"},
{"niveau":8,"quiz":"oui","prononciation":"いう","kanji":"言う","hint":"to say"},
{"niveau":8,"quiz":"oui","prononciation":"おもう","kanji":"思う","hint":"to think"},
{"niveau":8,"quiz":"oui","prononciation":"でんしゃ","kanji":"電車","hint":"train"},
{"niveau":9,"quiz":"non","prononciation":"はくし","kanji":"白紙","hint":"blank sheet ( し：紙)"},
{"niveau":9,"quiz":"non","prononciation":"ゆうめいな","kanji":"有名な","hint":"famous"},
{"niveau":9,"quiz":"non","prononciation":"すくない","kanji":"少ない","hint":"few"},
{"niveau":9,"quiz":"non","prononciation":"うち","kanji":"家","hint":"house, home"},
{"niveau":9,"quiz":"non","prononciation":"にんげん","kanji":"人間","hint":"human being"},
{"niveau":9,"quiz":"non","prononciation":"ちゅうこ","kanji":"中古","hint":"secondhand"},
{"niveau":9,"quiz":"non","prononciation":"しんゆう","kanji":"親友","hint":"best friend"},
{"niveau":9,"quiz":"non","prononciation":"ゆうじん","kanji":"友人","hint":"easy!"},
{"niveau":9,"quiz":"non","prononciation":"しょうしょう","kanji":"少々","hint":"a little"},
{"niveau":9,"quiz":"non","prononciation":"ちじん","kanji":"知人","hint":"acquaintance"},
{"niveau":9,"quiz":"non","prononciation":"かいわ","kanji":"会話","hint":"conversation"},
{"niveau":9,"quiz":"oui","prononciation":"いえ","kanji":"家","hint":"house"},
{"niveau":9,"quiz":"oui","prononciation":"ごぜんちゅう","kanji":"午前中","hint":"in the morning"},
{"niveau":9,"quiz":"oui","prononciation":"あとで","kanji":"後で","hint":"later"},
{"niveau":9,"quiz":"oui","prononciation":"すこし","kanji":"少し","hint":"little"},
{"niveau":9,"quiz":"oui","prononciation":"なまえ","kanji":"名前","hint":"name"},
{"niveau":9,"quiz":"oui","prononciation":"こない","kanji":"来ない","hint":"not come"},
{"niveau":9,"quiz":"oui","prononciation":"ふるい","kanji":"古い","hint":"old (things)"},
{"niveau":9,"quiz":"oui","prononciation":"はなし","kanji":"話","hint":"talk, story"},
{"niveau":9,"quiz":"oui","prononciation":"くる","kanji":"来る","hint":"to come"},
{"niveau":9,"quiz":"oui","prononciation":"しる","kanji":"知る","hint":"to know"},
{"niveau":9,"quiz":"oui","prononciation":"はなす","kanji":"話す","hint":"to speak"},
{"niveau":9,"quiz":"oui","prononciation":"しろい","kanji":"白い","hint":"white"},
{"niveau":9,"quiz":"oui","prononciation":"ごぜん","kanji":"午前","hint":"A.M."},
{"niveau":9,"quiz":"oui","prononciation":"ごご","kanji":"午後","hint":"afternoon"},
{"niveau":9,"quiz":"oui","prononciation":"あめ","kanji":"雨","hint":"easy!"},
{"niveau":9,"quiz":"oui","prononciation":"かく","kanji":"書く","hint":"easy!"},
{"niveau":9,"quiz":"oui","prononciation":"ともだち","kanji":"友だち","hint":"easy!"},
{"niveau":9,"quiz":"oui","prononciation":"じかん","kanji":"時間","hint":"easy!"},
{"niveau":9,"quiz":"oui","prononciation":"あいだ","kanji":"間","hint":"between"},
{"niveau":9,"quiz":"oui","prononciation":"にじかん","kanji":"二時間","hint":"easy!"},
{"niveau":9,"quiz":"oui","prononciation":"でんわ","kanji":"電話","hint":"easy!"},
{"niveau":9,"quiz":"oui","prononciation":"のあと","kanji":"の後","hint":"after..."},
{"niveau":9,"quiz":"oui","prononciation":"うしろ","kanji":"後ろ","hint":"back, behind"},
{"niveau":9,"quiz":"oui","prononciation":"まえ","kanji":"前","hint":"before, front"},
{"niveau":9,"quiz":"oui","prononciation":"きます","kanji":"来ます","hint":"come"},
{"niveau":10,"quiz":"non","prononciation":"じゅうしょ","kanji":"住所","hint":"address"},
{"niveau":10,"quiz":"non","prononciation":"ただしい","kanji":"正しい","hint":"right"},
{"niveau":10,"quiz":"non","prononciation":"ばいてん","kanji":"売店","hint":"stand, stall"},
{"niveau":10,"quiz":"non","prononciation":"かいもの","kanji":"買い物","hint":"shopping"},
{"niveau":10,"quiz":"non","prononciation":"きたやまちょう","kanji":"北山町","hint":"Kitayama town"},
{"niveau":10,"quiz":"non","prononciation":"ちょうちょう","kanji":"町長","hint":"mayor of a towm"},
{"niveau":10,"quiz":"non","prononciation":"ちょうなん","kanji":"長男","hint":"first son"},
{"niveau":10,"quiz":"non","prononciation":"しょどう","kanji":"書道","hint":"calligraphy"},
{"niveau":10,"quiz":"non","prononciation":" ほっかいどう","kanji":"北海道","hint":"north sea way"},
{"niveau":10,"quiz":"non","prononciation":"しんせつ","kanji":"新雪","hint":"new snow"},
{"niveau":10,"quiz":"non","prononciation":"こくりつだいがく","kanji":"国立大学","hint":"national university"},
{"niveau":10,"quiz":"non","prononciation":"しりつこうこう","kanji":"私立高校","hint":"private high school"},
{"niveau":10,"quiz":"non","prononciation":"じどうしゃ","kanji":"自動車","hint":"automobile"},
{"niveau":10,"quiz":"non","prononciation":"じてんしゃ","kanji":"自転車","hint":"bicycle"},
{"niveau":10,"quiz":"non","prononciation":"よなか","kanji":"夜中","hint":"midnight"},
{"niveau":10,"quiz":"non","prononciation":"こにゃ","kanji":"今夜","hint":"tonight"},
{"niveau":10,"quiz":"non","prononciation":"ちょうしょく","kanji":"朝食","hint":"breakfast"},
{"niveau":10,"quiz":"non","prononciation":"しょじひん","kanji":"所持品","hint":"しょ：所"},
{"niveau":10,"quiz":"oui","prononciation":"すむ","kanji":"住む","hint":"to live"},
{"niveau":10,"quiz":"oui","prononciation":"おしょうがつ","kanji":"お正月","hint":"New Year"},
{"niveau":10,"quiz":"oui","prononciation":"さんねんせい","kanji":"三年生","hint":"easy!"},
{"niveau":10,"quiz":"oui","prononciation":"らいねん","kanji":"来年","hint":"next year"},
{"niveau":10,"quiz":"oui","prononciation":"ことし","kanji":"今年","hint":"this year"},
{"niveau":10,"quiz":"oui","prononciation":"とし","kanji":"年","hint":"year"},
{"niveau":10,"quiz":"oui","prononciation":"うる","kanji":"売る","hint":"to sell"},
{"niveau":10,"quiz":"oui","prononciation":"かう","kanji":"買う","hint":"to buy"},
{"niveau":10,"quiz":"oui","prononciation":"まち","kanji":"町","hint":"town"},
{"niveau":10,"quiz":"oui","prononciation":"ながい","kanji":"長い","hint":"long"},
{"niveau":10,"quiz":"oui","prononciation":"みち","kanji":"道","hint":"way, road"},
{"niveau":10,"quiz":"oui","prononciation":"ゆき","kanji":"雪","hint":"snow"},
{"niveau":10,"quiz":"oui","prononciation":"たつ","kanji":"立つ","hint":"to stand"},
{"niveau":10,"quiz":"oui","prononciation":"じぶん","kanji":"自分","hint":"oneself"},
{"niveau":10,"quiz":"oui","prononciation":"よる","kanji":"夜","hint":"night"},
{"niveau":10,"quiz":"oui","prononciation":"あさ","kanji":"朝","hint":"morning"},
{"niveau":10,"quiz":"oui","prononciation":"けさ","kanji":"今朝","hint":"this morning"},
{"niveau":10,"quiz":"oui","prononciation":"もつ","kanji":"持つ","hint":"to hold"},
{"niveau":10,"quiz":"oui","prononciation":"もってくる","kanji":"持ってくる","hint":"to bring"},
{"niveau":11,"quiz":"non","prononciation":"て","kanji":"手","hint":"hand"},
{"niveau":11,"quiz":"non","prononciation":"しゅわ","kanji":"手話","hint":"sign language"},
{"niveau":11,"quiz":"non","prononciation":"じょうずな","kanji":"上手な","hint":"good at"},
{"niveau":11,"quiz":"non","prononciation":"わし","kanji":"和紙","hint":"Japanese paper"},
{"niveau":11,"quiz":"non","prononciation":"かみ","kanji":"紙","hint":"paper"},
{"niveau":11,"quiz":"non","prononciation":"このみ","kanji":"好み","hint":"taste, liking"},
{"niveau":11,"quiz":"non","prononciation":"あした","kanji":"明日","hint":"tomorrow"},
{"niveau":11,"quiz":"non","prononciation":"だいがくいん","kanji":"大学院","hint":"graduate school"},
{"niveau":11,"quiz":"non","prononciation":"うつる","kanji":"映る","hint":"to be reflected"},
{"niveau":11,"quiz":"non","prononciation":"がか","kanji":"画家","hint":"painter (picture house)"},
{"niveau":11,"quiz":"non","prononciation":"こっか","kanji":"国家","hint":"national anthem"},
{"niveau":11,"quiz":"non","prononciation":"しちょう","kanji":"市長","hint":"mayor"},
{"niveau":11,"quiz":"non","prononciation":"いろいろなところ","kanji":"いろいろな所","hint":"various places"},
{"niveau":11,"quiz":"non","prononciation":"じゅしょ","kanji":"住所","hint":"address"},
{"niveau":11,"quiz":"non","prononciation":"つとめる","kanji":"勉める","hint":"to try hard"},
{"niveau":11,"quiz":"non","prononciation":"ある","kanji":"有る","hint":"to exist"},
{"niveau":11,"quiz":"non","prononciation":"ひとりたび","kanji":"一人旅","hint":"traveling alone"},
{"niveau":11,"quiz":"oui","prononciation":"てがみ","kanji":"手紙","hint":"letter"},
{"niveau":11,"quiz":"oui","prononciation":"かしょ","kanji":"歌手","hint":"signer"},
{"niveau":11,"quiz":"oui","prononciation":"すきな","kanji":"好きな","hint":"to like"},
{"niveau":11,"quiz":"oui","prononciation":"ちかく","kanji":"近く","hint":"nearby"},
{"niveau":11,"quiz":"oui","prononciation":"きんじょ","kanji":"近所","hint":"neighborhood"},
{"niveau":11,"quiz":"oui","prononciation":"あかるい","kanji":"明るい","hint":"bright, cheerful"},
{"niveau":11,"quiz":"oui","prononciation":"びょういん","kanji":"病院","hint":"hospital"},
{"niveau":11,"quiz":"oui","prononciation":"びょうき","kanji":"病気","hint":"illness"},
{"niveau":11,"quiz":"oui","prononciation":"えいが","kanji":"映画","hint":"movie (reflect picture)"},
{"niveau":11,"quiz":"oui","prononciation":"うたう","kanji":"歌う","hint":"to sing"},
{"niveau":11,"quiz":"oui","prononciation":"うた","kanji":"歌","hint":"song"},
{"niveau":11,"quiz":"oui","prononciation":"かわぐちし","kanji":"川口市","hint":"Kawaguchi city"},
{"niveau":11,"quiz":"oui","prononciation":"ところ","kanji":"所","hint":"place"},
{"niveau":11,"quiz":"oui","prononciation":"べんきょうする","kanji":"勉強する","hint":"to study"},
{"niveau":11,"quiz":"oui","prononciation":"つよい","kanji":"強い","hint":"strong"},
{"niveau":11,"quiz":"oui","prononciation":"ゆうめい","kanji":"有名","hint":"easy!"},
{"niveau":11,"quiz":"oui","prononciation":"りょこう","kanji":"旅行","hint":"travel"},
{"niveau":12,"quiz":"non","prononciation":"むかしばなし","kanji":"昔話","hint":"old tale"},
{"niveau":12,"quiz":"non","prononciation":"ときどき","kanji":"時々","hint":"repeated kanji"},
{"niveau":12,"quiz":"non","prononciation":"いろいろな","kanji":"色々な","hint":"repeated kanji"},
{"niveau":12,"quiz":"non","prononciation":"しんと","kanji":"神道","hint":"god way"},
{"niveau":12,"quiz":"non","prononciation":"そうちょう","kanji":"早朝","hint":"early morning"},
{"niveau":12,"quiz":"non","prononciation":"はやおきする","kanji":"早起きする","hint":"to get up early"},
{"niveau":12,"quiz":"non","prononciation":"おこす","kanji":"起こす","hint":"to wake someone up"},
{"niveau":12,"quiz":"non","prononciation":"きりつする","kanji":"起立する","hint":"to stand up"},
{"niveau":12,"quiz":"non","prononciation":"ぎゅうにく","kanji":"牛肉","hint":"beef"},
{"niveau":12,"quiz":"non","prononciation":"たいし","kanji":"大使","hint":"embassador"},
{"niveau":12,"quiz":"non","prononciation":"ともばたらき","kanji":"共働き","hint":"both husband and wife working for a living  (とも：共)"},
{"niveau":12,"quiz":"non","prononciation":"こくれん","kanji":"国連","hint":"United Nations"},
{"niveau":12,"quiz":"non","prononciation":"れんきゅう","kanji":"連休","hint":"consecutive holidays"},
{"niveau":12,"quiz":"non","prononciation":"とくべつに","kanji":"特別に","hint":"special"},
{"niveau":12,"quiz":"non","prononciation":"べつべつに","kanji":"別々に","hint":"separately"},
{"niveau":12,"quiz":"non","prononciation":"ど","kanji":"度","hint":"degrees"},
{"niveau":12,"quiz":"non","prononciation":"あかちゃん","kanji":"赤ちゃん","hint":"baby"},
{"niveau":12,"quiz":"non","prononciation":"せきどう","kanji":"赤道","hint":"the equator (red way)"},
{"niveau":12,"quiz":"non","prononciation":"せきじゅうじ","kanji":"赤十字","hint":"the Red cross (じ：字)"},
{"niveau":12,"quiz":"non","prononciation":"せいねん","kanji":"青年","hint":"youth (blue year)"},
{"niveau":12,"quiz":"non","prononciation":"とくしょく","kanji":"特色","hint":"characteristic (とく：特)"},
{"niveau":12,"quiz":"oui","prononciation":"むかし","kanji":"昔","hint":"old times"},
{"niveau":12,"quiz":"oui","prononciation":"むかしむかし","kanji":"昔々","hint":"once upon a time"},
{"niveau":12,"quiz":"oui","prononciation":"ひとびと","kanji":"人々","hint":"people"},
{"niveau":12,"quiz":"oui","prononciation":"かみさま","kanji":"神さま","hint":"God"},
{"niveau":12,"quiz":"oui","prononciation":"じんじゃ","kanji":"神社","hint":"shrine (god company)"},
{"niveau":12,"quiz":"oui","prononciation":"はやい","kanji":"早い","hint":"early"},
{"niveau":12,"quiz":"oui","prononciation":"おきる","kanji":"起きる","hint":"to get up"},
{"niveau":12,"quiz":"oui","prononciation":"うし","kanji":"牛","hint":"cow"},
{"niveau":12,"quiz":"oui","prononciation":"つかう","kanji":"使う","hint":"to use"},
{"niveau":12,"quiz":"oui","prononciation":"はたらく","kanji":"働く","hint":"to work"},
{"niveau":12,"quiz":"oui","prononciation":"つれてかえる","kanji":"連れて帰る","hint":"to take home"},
{"niveau":12,"quiz":"oui","prononciation":"わかれる","kanji":"別れる","hint":"to seperate"},
{"niveau":12,"quiz":"oui","prononciation":"べつに","kanji":"別に","hint":"not in particular"},
{"niveau":12,"quiz":"oui","prononciation":"いちど","kanji":"一度","hint":"once"},
{"niveau":12,"quiz":"oui","prononciation":"こんど","kanji":"今度","hint":"near future"},
{"niveau":12,"quiz":"oui","prononciation":"あかい","kanji":"赤い","hint":"red"},
{"niveau":12,"quiz":"oui","prononciation":"あおい","kanji":"青い","hint":"blue"},
{"niveau":12,"quiz":"oui","prononciation":"いろ","kanji":"色","hint":"color "},
{"niveau":13,"quiz":"non","prononciation":"はくちょう","kanji":"白鳥","hint":"swan"},
{"niveau":13,"quiz":"non","prononciation":"りょうきん","kanji":"料金","hint":"fare reason"},
{"niveau":13,"quiz":"non","prononciation":"とくべつに","kanji":"特別に","hint":"special"},
{"niveau":13,"quiz":"non","prononciation":"とっきゅうでんしゃ","kanji":"特急電車","hint":"super express train"},
{"niveau":13,"quiz":"non","prononciation":"ぎゅうにく","kanji":"牛肉","hint":"beef"},
{"niveau":13,"quiz":"non","prononciation":"にくや","kanji":"肉屋","hint":"や：屋"},
{"niveau":13,"quiz":"non","prononciation":"そら","kanji":"空","hint":"sky"},
{"niveau":13,"quiz":"non","prononciation":"あく","kanji":"空く","hint":"to be vacant"},
{"niveau":13,"quiz":"non","prononciation":"からて","kanji":"空手","hint":"sky hand"},
{"niveau":13,"quiz":"non","prononciation":"みなと","kanji":"港","hint":"port"},
{"niveau":13,"quiz":"non","prononciation":"どうじ","kanji":"同時","hint":"simultaneous (same time)"},
{"niveau":13,"quiz":"non","prononciation":"にほんかい","kanji":"日本海","hint":"the Japan Sea"},
{"niveau":13,"quiz":"non","prononciation":"かいがい","kanji":"海外","hint":"overseas"},
{"niveau":13,"quiz":"non","prononciation":"ちゅうしょく","kanji":"昼食","hint":"lunch (noon eat)"},
{"niveau":13,"quiz":"non","prononciation":"きゅうこう","kanji":"急行","hint":"express train"},
{"niveau":13,"quiz":"non","prononciation":"とっきゅう","kanji":"特急","hint":"super express"},
{"niveau":13,"quiz":"non","prononciation":"のりもの","kanji":"乗り物","hint":"vehicle"},
{"niveau":13,"quiz":"non","prononciation":"じょうしゃ","kanji":"乗車","hint":"riding a car"},
{"niveau":13,"quiz":"non","prononciation":"じょうば","kanji":"乗馬","hint":"horseback riding (ば：馬)"},
{"niveau":13,"quiz":"non","prononciation":"とうじ","kanji":"当時","hint":"at that time (hit time)"},
{"niveau":13,"quiz":"non","prononciation":"あたる","kanji":"当たる","hint":"to hit"},
{"niveau":13,"quiz":"non","prononciation":"おと","kanji":"音","hint":"sound"},
{"niveau":13,"quiz":"non","prononciation":"らくな","kanji":"楽な","hint":"easy, confortable"},
{"niveau":13,"quiz":"non","prononciation":"いかく","kanji":"医学","hint":"medical science"},
{"niveau":13,"quiz":"non","prononciation":"いいん","kanji":"医院","hint":"clinic"},
{"niveau":13,"quiz":"non","prononciation":"がくしゃ","kanji":"学者","hint":"scholar (learn person)"},
{"niveau":13,"quiz":"non","prononciation":"どくしゃ","kanji":"読者","hint":"reader (read person)"},
{"niveau":13,"quiz":"non","prononciation":"ろくねんかん","kanji":"六年間","hint":"during 6 years"},
{"niveau":13,"quiz":"non","prononciation":"さんかげつご","kanji":"三ヶ月後","hint":"after 3 months"},
{"niveau":13,"quiz":"oui","prononciation":"もの","kanji":"物","hint":"things"},
{"niveau":13,"quiz":"oui","prononciation":"たべもの","kanji":"食べ物","hint":"food"},
{"niveau":13,"quiz":"oui","prononciation":"かいもの","kanji":"買い物","hint":"shopping"},
{"niveau":13,"quiz":"oui","prononciation":"とり","kanji":"鳥","hint":"bird"},
{"niveau":13,"quiz":"oui","prononciation":"りょうり","kanji":"料理","hint":"ingredients reason"},
{"niveau":13,"quiz":"oui","prononciation":"とくに","kanji":"特に","hint":"especially"},
{"niveau":13,"quiz":"oui","prononciation":"やすい","kanji":"安い","hint":"cheap"},
{"niveau":13,"quiz":"oui","prononciation":"ごはん","kanji":"ご飯","hint":"rice meal"},
{"niveau":13,"quiz":"oui","prononciation":"あさごはん","kanji":"朝ご飯","hint":"breakfast"},
{"niveau":13,"quiz":"oui","prononciation":"にく","kanji":"肉","hint":"meat"},
{"niveau":13,"quiz":"oui","prononciation":"わるい","kanji":"悪い","hint":"bad"},
{"niveau":13,"quiz":"oui","prononciation":"きぶんがわるい","kanji":"気分が悪い","hint":"to feel sick"},
{"niveau":13,"quiz":"oui","prononciation":"からだ","kanji":"体","hint":"body"},
{"niveau":13,"quiz":"oui","prononciation":"くうこう","kanji":"空港","hint":"sky port"},
{"niveau":13,"quiz":"oui","prononciation":"くうき","kanji":"空気","hint":"air"},
{"niveau":13,"quiz":"oui","prononciation":"つく","kanji":"着く","hint":"to arrive"},
{"niveau":13,"quiz":"oui","prononciation":"きる","kanji":"着る","hint":"to wear"},
{"niveau":13,"quiz":"oui","prononciation":"きもの","kanji":"着物","hint":"to wear thing"},
{"niveau":13,"quiz":"oui","prononciation":"おなじ","kanji":"同じ","hint":"same"},
{"niveau":13,"quiz":"oui","prononciation":"うみ","kanji":"海","hint":"sea"},
{"niveau":13,"quiz":"oui","prononciation":"ひる","kanji":"昼","hint":"noon, daytime"},
{"niveau":13,"quiz":"oui","prononciation":"ひるごはん","kanji":"昼ご飯","hint":"lunch (noon food)"},
{"niveau":13,"quiz":"oui","prononciation":"きゅうに","kanji":"急に","hint":"suddenly"},
{"niveau":13,"quiz":"oui","prononciation":"いそぐ","kanji":"急ぐ","hint":"to hurry"},
{"niveau":13,"quiz":"oui","prononciation":"のる","kanji":"乗る","hint":"to ride"},
{"niveau":13,"quiz":"oui","prononciation":"ほんとうに","kanji":"本当に","hint":"really"},
{"niveau":13,"quiz":"oui","prononciation":"おんがく","kanji":"音楽","hint":"music (sound pleasure)"},
{"niveau":13,"quiz":"oui","prononciation":"たのしい","kanji":"楽しい","hint":"fun"},
{"niveau":13,"quiz":"oui","prononciation":"いしゃ","kanji":"医者","hint":"doctor (medicine person)"},
{"niveau":14,"quiz":"non","prononciation":"でんきだい","kanji":"電気代","hint":"electricity fee"},
{"niveau":14,"quiz":"non","prononciation":"ろくじゅうねんだい","kanji":"六十年代","hint":"the 60's"},
{"niveau":14,"quiz":"non","prononciation":"じゅうだい","kanji":"十代","hint":"teen"},
{"niveau":14,"quiz":"non","prononciation":"かわりに","kanji":"代わりに","hint":"instead"},
{"niveau":14,"quiz":"non","prononciation":"かきとめ","kanji":"書き留め","hint":"registered mail"},
{"niveau":14,"quiz":"non","prononciation":"しんゆう","kanji":"親友","hint":"best friend"},
{"niveau":14,"quiz":"non","prononciation":"したしい","kanji":"親しい","hint":"intimate"},
{"niveau":14,"quiz":"non","prononciation":"たいせつな","kanji":"大切な","hint":"precious"},
{"niveau":14,"quiz":"non","prononciation":"きって","kanji":"切手","hint":"post stamp"},
{"niveau":14,"quiz":"non","prononciation":"えいこく","kanji":"英国","hint":" England"},
{"niveau":14,"quiz":"non","prononciation":"えいかいわ","kanji":"英会話","hint":"English conversation"},
{"niveau":14,"quiz":"non","prononciation":"てんいん","kanji":"店員","hint":"store attendant"},
{"niveau":14,"quiz":"non","prononciation":"ばいてん","kanji":"売店","hint":"stall"},
{"niveau":14,"quiz":"non","prononciation":"しょてん","kanji":"書店","hint":"book store"},
{"niveau":14,"quiz":"non","prononciation":"としうえ","kanji":"年上","hint":"being older (year over)"},
{"niveau":14,"quiz":"non","prononciation":"さる","kanji":"去る","hint":"to leave"},
{"niveau":14,"quiz":"oui","prononciation":"かれ","kanji":"彼","hint":"he, boyfriend"},
{"niveau":14,"quiz":"oui","prononciation":"かのじょ","kanji":"彼女","hint":"she, girlfriend"},
{"niveau":14,"quiz":"oui","prononciation":"じだい","kanji":"時代","hint":"era (time age)"},
{"niveau":14,"quiz":"oui","prononciation":"りゅうがくせい","kanji":"留学生","hint":"foreign student"},
{"niveau":14,"quiz":"oui","prononciation":"かぞく","kanji":"家族","hint":"family"},
{"niveau":14,"quiz":"oui","prononciation":"ちちおや","kanji":"父親","hint":"father"},
{"niveau":14,"quiz":"oui","prononciation":"しんせtるな","kanji":"親切な","hint":"kind"},
{"niveau":14,"quiz":"oui","prononciation":"きる","kanji":"切る","hint":"to cut"},
{"niveau":14,"quiz":"oui","prononciation":"えいご","kanji":"英語","hint":"English"},
{"niveau":14,"quiz":"oui","prononciation":"みせ","kanji":"店","hint":"shop"},
{"niveau":14,"quiz":"oui","prononciation":"きょねん","kanji":"去年","hint":"last year"},
{"niveau":15,"quiz":"non","prononciation":"し","kanji":"死","hint":"death"},
{"niveau":15,"quiz":"non","prononciation":"あんらくし","kanji":"安楽死","hint":"euthanasia"},
{"niveau":15,"quiz":"non","prononciation":"いけん","kanji":"意見","hint":"opinion (mind see)"},
{"niveau":15,"quiz":"non","prononciation":"あじ","kanji":"味","hint":"taste (flavor)"},
{"niveau":15,"quiz":"non","prononciation":"ちゅうもんする","kanji":"注文する","hint":"to order"},
{"niveau":15,"quiz":"non","prononciation":"そそぐ","kanji":"注ぐ","hint":"to pour"},
{"niveau":15,"quiz":"non","prononciation":"きんぎょ","kanji":"金魚","hint":"goldfish"},
{"niveau":15,"quiz":"non","prononciation":"とうじ","kanji":"東寺","hint":"temple Toji (east temple)"},
{"niveau":15,"quiz":"non","prononciation":"うんてんする","kanji":"運転する","hint":"to drive"},
{"niveau":15,"quiz":"non","prononciation":"かいてんずし","kanji":"回転ずし","hint":"rotating sushi"},
{"niveau":15,"quiz":"non","prononciation":"ころぶ","kanji":"転ぶ","hint":"to stumble, to fall down (roll over)"},
{"niveau":15,"quiz":"non","prononciation":"しゃくち","kanji":"借地","hint":"rented land (borrow land)"},
{"niveau":15,"quiz":"non","prononciation":"しゃっきん","kanji":"借金","hint":"debt (borrow money)"},
{"niveau":15,"quiz":"non","prononciation":"はしりがき","kanji":"走り書き","hint":"hasty writing"},
{"niveau":15,"quiz":"non","prononciation":"たてる","kanji":"建てる","hint":"to build"},
{"niveau":15,"quiz":"non","prononciation":"たつ","kanji":"建つ","hint":"to be build"},
{"niveau":15,"quiz":"non","prononciation":"けんこく","kanji":"建国","hint":"founding a nation"},
{"niveau":15,"quiz":"non","prononciation":"ばしょ","kanji":"場所","hint":"place"},
{"niveau":15,"quiz":"non","prononciation":"たりる","kanji":"足りる","hint":"to be sufficient"},
{"niveau":15,"quiz":"non","prononciation":"いっそく","kanji":"一足","hint":"one pair of shoes (one foot)"},
{"niveau":15,"quiz":"non","prononciation":"かよう","kanji":"通う","hint":"to commute"},
{"niveau":15,"quiz":"non","prononciation":"つうがく","kanji":"通学","hint":"going to school"},
{"niveau":15,"quiz":"non","prononciation":"つうきん","kanji":"通勤","hint":"going to work"},
{"niveau":15,"quiz":"oui","prononciation":"しぬ","kanji":"死ぬ","hint":"to die"},
{"niveau":15,"quiz":"oui","prononciation":"いみ","kanji":"意味","hint":"meaning (mind flavor)"},
{"niveau":15,"quiz":"oui","prononciation":"ちゅういする","kanji":"注意する","hint":"to watch out"},
{"niveau":15,"quiz":"oui","prononciation":"なつ","kanji":"夏","hint":"summer"},
{"niveau":15,"quiz":"oui","prononciation":"なつやすみ","kanji":"夏休み","hint":"summer vacation"},
{"niveau":15,"quiz":"oui","prononciation":"さかな","kanji":"魚","hint":"fish"},
{"niveau":15,"quiz":"oui","prononciation":"おてら","kanji":"お寺","hint":"temple"},
{"niveau":15,"quiz":"oui","prononciation":"ひろい","kanji":"広い","hint":"wide, spacious"},
{"niveau":15,"quiz":"oui","prononciation":"ひろば","kanji":"広場","hint":"square, open space"},
{"niveau":15,"quiz":"oui","prononciation":"じてんしゃ","kanji":"自転車","hint":"bicycle"},
{"niveau":15,"quiz":"oui","prononciation":"かりる","kanji":"借りる","hint":"to borrow"},
{"niveau":15,"quiz":"oui","prononciation":"はしる","kanji":"走る","hint":"to run"},
{"niveau":15,"quiz":"oui","prononciation":"たてもの","kanji":"建物","hint":"building"},
{"niveau":15,"quiz":"oui","prononciation":"ちか","kanji":"地下","hint":"underground"},
{"niveau":15,"quiz":"oui","prononciation":"あし","kanji":"足","hint":"foot, leg"},
{"niveau":15,"quiz":"oui","prononciation":"とおる","kanji":"通る","hint":"to pass, to go through"},
{"niveau":16,"quiz":"non","prononciation":"ともに","kanji":"ともに","hint":"together"},
{"niveau":16,"quiz":"non","prononciation":"そなえる","kanji":"供える","hint":"offer something to the spirit"},
{"niveau":16,"quiz":"non","prononciation":"せわ","kanji":"世話","hint":"care"},
{"niveau":16,"quiz":"non","prononciation":"せだい","kanji":"世代","hint":"generation"},
{"niveau":16,"quiz":"non","prononciation":"さんせい","kanji":"三世","hint":"the 3rd generation"},
{"niveau":16,"quiz":"non","prononciation":"よのなか","kanji":"世の中","hint":"the society"},
{"niveau":16,"quiz":"non","prononciation":"あんぜん","kanji":"安全","hint":"safety (cheap all)"},
{"niveau":16,"quiz":"non","prononciation":"ぜんこく","kanji":"全国","hint":"whole country"},
{"niveau":16,"quiz":"non","prononciation":"まったく","kanji":"全く","hint":"entirely"},
{"niveau":16,"quiz":"non","prononciation":"テニスぶ","kanji":"テニス部","hint":"tennis club"},
{"niveau":16,"quiz":"non","prononciation":"ぶちょう","kanji":"部長","hint":"department manager"},
{"niveau":16,"quiz":"non","prononciation":"～いか","kanji":"～以下","hint":"~or less"},
{"niveau":16,"quiz":"non","prononciation":"いご","kanji":"以後","hint":"hereafter"},
{"niveau":16,"quiz":"non","prononciation":"いぜん","kanji":"以前","hint":"before, formerly"},
{"niveau":16,"quiz":"non","prononciation":"かんがえ","kanji":"考え","hint":"idea"},
{"niveau":16,"quiz":"non","prononciation":"こうこがく","kanji":"考古学","hint":"archeology"},
{"niveau":16,"quiz":"non","prononciation":"あく","kanji":"開く","hint":"something opens"},
{"niveau":16,"quiz":"non","prononciation":"ひらく","kanji":"開く","hint":"to open"},
{"niveau":16,"quiz":"non","prononciation":"かいてん","kanji":"開店","hint":"opening of a store"},
{"niveau":16,"quiz":"non","prononciation":"さかなや","kanji":"魚屋","hint":"fish shop"},
{"niveau":16,"quiz":"non","prononciation":"おくじょう","kanji":"屋上","hint":"rooftop"},
{"niveau":16,"quiz":"non","prononciation":"よみかた","kanji":"読み方","hint":"way of reading"},
{"niveau":16,"quiz":"non","prononciation":"うんがいい","kanji":"運がいい","hint":"lucky"},
{"niveau":16,"quiz":"non","prononciation":"はこぶ","kanji":"運ぶ","hint":"to carry"},
{"niveau":16,"quiz":"non","prononciation":"うごく","kanji":"動く","hint":"to move"},
{"niveau":16,"quiz":"non","prononciation":"じどうしゃ","kanji":"自動車","hint":"automobile"},
{"niveau":16,"quiz":"non","prononciation":"どうぶつ","kanji":"動物","hint":"animal (thing move)"},
{"niveau":16,"quiz":"non","prononciation":"きょうかい","kanji":"教会","hint":"church"},
{"niveau":16,"quiz":"non","prononciation":"きょうかしょ","kanji":"教科書","hint":"textbook"},
{"niveau":16,"quiz":"non","prononciation":"いちねんじゅう","kanji":"一年中","hint":"all year"},
{"niveau":16,"quiz":"non","prononciation":"ちかしつ","kanji":"地下室","hint":"basement"},
{"niveau":16,"quiz":"non","prononciation":"にんき","kanji":"人気","hint":"popularity"},
{"niveau":16,"quiz":"non","prononciation":"おかねもち","kanji":"お金持ち","hint":"rich person"},
{"niveau":16,"quiz":"oui","prononciation":"こども","kanji":"子供","hint":"child companion"},
{"niveau":16,"quiz":"oui","prononciation":"せかい","kanji":"世界","hint":"the world"},
{"niveau":16,"quiz":"oui","prononciation":"ぜんぶ","kanji":"全部","hint":"all part"},
{"niveau":16,"quiz":"oui","prononciation":"へや","kanji":"部屋","hint":"room"},
{"niveau":16,"quiz":"oui","prononciation":"はじまる","kanji":"始まる","hint":"something begins"},
{"niveau":16,"quiz":"oui","prononciation":"まいしゅう","kanji":"毎週","hint":"every week"},
{"niveau":16,"quiz":"oui","prononciation":"せんしゅう","kanji":"先週","hint":"last week"},
{"niveau":16,"quiz":"oui","prononciation":"～いじょう","kanji":"～以上","hint":"~or more"},
{"niveau":16,"quiz":"oui","prononciation":"かんがえる","kanji":"考える","hint":"to think"},
{"niveau":16,"quiz":"oui","prononciation":"あける","kanji":"開ける","hint":"to open something"},
{"niveau":16,"quiz":"oui","prononciation":"ほんや","kanji":"本屋","hint":"bookstore"},
{"niveau":16,"quiz":"oui","prononciation":"みかた","kanji":"味方","hint":" person to one's side (taste person)"},
{"niveau":16,"quiz":"oui","prononciation":"うんどうする","kanji":"運動する","hint":"do exercises"},
{"niveau":16,"quiz":"oui","prononciation":"うんてんする","kanji":"運転する","hint":"drive"},
{"niveau":16,"quiz":"oui","prononciation":"おしえる","kanji":"教える","hint":"to teach"},
{"niveau":16,"quiz":"oui","prononciation":"きょうしつ","kanji":"教室","hint":"classroom (teach room)"},
{"niveau":17,"quiz":"non","prononciation":"しはつ","kanji":"始発","hint":"first train"},
{"niveau":17,"quiz":"non","prononciation":"しゅうじ","kanji":"習字","hint":"calligraphy"},
{"niveau":17,"quiz":"non","prononciation":"しょご","kanji":"主語","hint":"subject of a sentence (main language)"},
{"niveau":17,"quiz":"non","prononciation":"もちぬし","kanji":"持ち主","hint":"owner"},
{"niveau":17,"quiz":"non","prononciation":"むすぶ","kanji":"結ぶ","hint":"to tie a knot"},
{"niveau":17,"quiz":"non","prononciation":"とくしゅう","kanji":"特集","hint":"magazine feature (special gather)"},
{"niveau":17,"quiz":"non","prononciation":" しゅうちゅうする","kanji":"集中する","hint":"to concentrate (gather inside)"},
{"niveau":17,"quiz":"non","prononciation":"はつおん","kanji":"発音","hint":"pronunciation (express way)"},
{"niveau":17,"quiz":"non","prononciation":"しゅっぱつ","kanji":"出発","hint":"departure (exit reveal)"},
{"niveau":17,"quiz":"non","prononciation":"あらわす","kanji":"表す","hint":"to express"},
{"niveau":17,"quiz":"non","prononciation":"じょうひんな","kanji":"上品な","hint":"elegant (up refinement)"},
{"niveau":17,"quiz":"non","prononciation":"しなもの","kanji":"品物","hint":"merchandise article (goods thing)"},
{"niveau":17,"quiz":"non","prononciation":"あかじ","kanji":"赤字","hint":"deficit (red character)"},
{"niveau":17,"quiz":"non","prononciation":"みょうじ","kanji":"名字","hint":"family name (name letter)"},
{"niveau":17,"quiz":"non","prononciation":"おおもじ","kanji":"大文字","hint":"uppercase letters (big sentence letter)"},
{"niveau":17,"quiz":"non","prononciation":"かっぱつな","kanji":"活発な","hint":"active (lively reveal)"},
{"niveau":17,"quiz":"non","prononciation":"しゃせい","kanji":"写生","hint":"sketch"},
{"niveau":17,"quiz":"non","prononciation":"うつす","kanji":"写す","hint":"to copy"},
{"niveau":17,"quiz":"non","prononciation":"まんなか","kanji":"真ん中","hint":"center (true inside)"},
{"niveau":17,"quiz":"non","prononciation":"のまうえ","kanji":"の真上","hint":"right above ~ (true up)"},
{"niveau":17,"quiz":"non","prononciation":"まよなか","kanji":"真夜中","hint":"midnight (true night inside)"},
{"niveau":17,"quiz":"oui","prononciation":"にじゅうごさい","kanji":"二十五歳","hint":"25 years old"},
{"niveau":17,"quiz":"oui","prononciation":"ならう","kanji":"習う","hint":"to learn"},
{"niveau":17,"quiz":"oui","prononciation":"おもに","kanji":"主に","hint":"mainly"},
{"niveau":17,"quiz":"oui","prononciation":"ごしゅじん","kanji":"ご主人","hint":"husband"},
{"niveau":17,"quiz":"oui","prononciation":"けっこんする","kanji":"結婚する","hint":"to marry"},
{"niveau":17,"quiz":"oui","prononciation":"あつめる","kanji":"集める","hint":"to collect"},
{"niveau":17,"quiz":"oui","prononciation":"はっぴょうする","kanji":"発表する","hint":"to make public (to reveal express)"},
{"niveau":17,"quiz":"oui","prononciation":"さくひん","kanji":"作品","hint":"piece of work (make refinement)"},
{"niveau":17,"quiz":"oui","prononciation":"もじ","kanji":"文字","hint":"character"},
{"niveau":17,"quiz":"oui","prononciation":"かつどう","kanji":"活動","hint":"activity"},
{"niveau":17,"quiz":"oui","prononciation":"せいかつ","kanji":"生活","hint":"daily life (next lively)"},
{"niveau":17,"quiz":"oui","prononciation":"しゃしん","kanji":"写真","hint":"photograph"},
{"niveau":17,"quiz":"oui","prononciation":"あるく","kanji":"歩く","hint":"to walk"},
{"niveau":17,"quiz":"oui","prononciation":"ぶんや","kanji":"分野","hint":"realm, field"},
{"niveau":17,"quiz":"oui","prononciation":"おのさん","kanji":"小野さん","hint":"Mr. small field"},
{"niveau":18,"quiz":"non","prononciation":"めうえのひと","kanji":"目上の人","hint":"one's superiors"},
{"niveau":18,"quiz":"non","prononciation":"しゃかいてき","kanji":"社会的","hint":"modern"},
{"niveau":18,"quiz":"non","prononciation":"まと","kanji":"的","hint":"target"},
{"niveau":18,"quiz":"non","prononciation":"りきし","kanji":"力士","hint":"sumo wrestler"},
{"niveau":18,"quiz":"non","prononciation":"とうよう","kanji":"東洋","hint":"Asia"},
{"niveau":18,"quiz":"non","prononciation":"ようしょく","kanji":"洋食","hint":"Western food"},
{"niveau":18,"quiz":"non","prononciation":"たいせいよう","kanji":"大西洋","hint":"the Atlantic (big west ocean)"},
{"niveau":18,"quiz":"non","prononciation":"どうどうとした","kanji":"堂々とした","hint":"dignified, imposing (hall hall)"},
{"niveau":18,"quiz":"non","prononciation":"きょうじゅ","kanji":"教授","hint":"professor"},
{"niveau":18,"quiz":"non","prononciation":"さずかる","kanji":"授かる","hint":"to be given"},
{"niveau":18,"quiz":"non","prononciation":"サービスぎょう","kanji":"サービス業","hint":"service industry"},
{"niveau":18,"quiz":"non","prononciation":"じょしがくせい","kanji":"女子学生","hint":"female student"},
{"niveau":18,"quiz":"non","prononciation":"だんしがくせい","kanji":"男子学生","hint":"male student"},
{"niveau":18,"quiz":"non","prononciation":"みっか","kanji":"三日","hint":"3 days"},
{"niveau":18,"quiz":"non","prononciation":"まいつき","kanji":"毎月","hint":"every month"},
{"niveau":18,"quiz":"non","prononciation":"でんきだい","kanji":"電気代","hint":"electricity fee"},
{"niveau":18,"quiz":"oui","prononciation":"もくてき","kanji":"目的","hint":"purpose (eye target)"},
{"niveau":18,"quiz":"oui","prononciation":"ちからしごと","kanji":"力仕事","hint":"physical labor (power work)"},
{"niveau":18,"quiz":"oui","prononciation":"ようふく","kanji":"洋服","hint":"clothes"},
{"niveau":18,"quiz":"oui","prononciation":"ふく","kanji":"服","hint":"clothes"},
{"niveau":18,"quiz":"oui","prononciation":"しょくどう","kanji":"食堂","hint":"dining room"},
{"niveau":18,"quiz":"oui","prononciation":"じゅぎょう","kanji":"授業","hint":"class"},
{"niveau":19,"quiz":"non","prononciation":"しゅんぶん","kanji":"春分","hint":"vernal equinox"},
{"niveau":19,"quiz":"non","prononciation":"せいしゅん","kanji":"青春","hint":"youth"},
{"niveau":19,"quiz":"non","prononciation":"しゅうぶん","kanji":"秋分","hint":"autumn equinox"},
{"niveau":19,"quiz":"non","prononciation":"はなみ","kanji":"花見","hint":"flower viewing"},
{"niveau":19,"quiz":"non","prononciation":"はなび","kanji":"花火","hint":"fireworks (flower fire)"},
{"niveau":19,"quiz":"non","prononciation":"ようす","kanji":"様子","hint":"manner (condition child)"},
{"niveau":19,"quiz":"non","prononciation":"ふけい","kanji":"父兄","hint":"guardians (father brother)"},
{"niveau":19,"quiz":"non","prononciation":"こうじ","kanji":"工事","hint":"construction (construction thing)"},
{"niveau":19,"quiz":"non","prononciation":"だいく","kanji":"大工","hint":"carpenter (big construction)"},
{"niveau":19,"quiz":"non","prononciation":"こうじょう","kanji":"工場","hint":"factory (construction place)"},
{"niveau":19,"quiz":"non","prononciation":"とぐ","kanji":"研ぐ","hint":"to sharpen (study)"},
{"niveau":19,"quiz":"non","prononciation":"きわめる","kanji":"究める","hint":"to investigate thoroughly (research)"},
{"niveau":19,"quiz":"non","prononciation":"しつがいい","kanji":"質がいい","hint":"good quality"},
{"niveau":19,"quiz":"non","prononciation":"しちや","kanji":"質屋","hint":"pawn shop (quality room)"},
{"niveau":19,"quiz":"non","prononciation":"もんだい","kanji":"問題","hint":"question topic"},
{"niveau":19,"quiz":"non","prononciation":"とう","kanji":"問う","hint":"to question"},
{"niveau":19,"quiz":"non","prononciation":"のおおく","kanji":"の多く","hint":"many of"},
{"niveau":19,"quiz":"oui","prononciation":"はる","kanji":"春","hint":"spring"},
{"niveau":19,"quiz":"oui","prononciation":"あき","kanji":"秋","hint":"autumn"},
{"niveau":19,"quiz":"oui","prononciation":"ふゆ","kanji":"冬","hint":"winter"},
{"niveau":19,"quiz":"oui","prononciation":"ふゆやすみ","kanji":"冬休み","hint":"winter vacation"},
{"niveau":19,"quiz":"oui","prononciation":"はな","kanji":"花","hint":"flower"},
{"niveau":19,"quiz":"oui","prononciation":"～さま","kanji":"～様","hint":"honorable mister"},
{"niveau":19,"quiz":"oui","prononciation":"ふあんな","kanji":"不安な","hint":"uneasy, worried (non cheap)"},
{"niveau":19,"quiz":"oui","prononciation":"あね","kanji":"姉","hint":"my older sister"},
{"niveau":19,"quiz":"oui","prononciation":"おねえさん","kanji":"お姉さん","hint":"someone else's older sister"},
{"niveau":19,"quiz":"oui","prononciation":"あに","kanji":"兄","hint":"my older brother"},
{"niveau":19,"quiz":"oui","prononciation":"おにいさん","kanji":"お兄さん","hint":"someone else's older brother"},
{"niveau":19,"quiz":"oui","prononciation":"かんじ","kanji":"漢字","hint":"Chinese character"},
{"niveau":19,"quiz":"oui","prononciation":"そつぎょうする","kanji":"卒業する","hint":"to graduate"},
{"niveau":19,"quiz":"oui","prononciation":"こうがく","kanji":"工学","hint":"engineering"},
{"niveau":19,"quiz":"oui","prononciation":"けんきゅう","kanji":"研究","hint":"research"},
{"niveau":19,"quiz":"oui","prononciation":"しつもん","kanji":"質問","hint":"question  "},
{"niveau":19,"quiz":"oui","prononciation":"おおい","kanji":"多い","hint":"many"},
{"niveau":20,"quiz":"non","prononciation":"おんせいがく","kanji":"音声学","hint":"phonetics"},
{"niveau":20,"quiz":"non","prononciation":"むせいえいが","kanji":"無声映画","hint":"silent movie"},
{"niveau":20,"quiz":"non","prononciation":"ちゅうしする","kanji":"中止する","hint":"to cancel"},
{"niveau":20,"quiz":"non","prononciation":"りょうて","kanji":"両手","hint":"both hands"},
{"niveau":20,"quiz":"non","prononciation":"りょうほう","kanji":"両方","hint":"both sides"},
{"niveau":20,"quiz":"non","prononciation":"むりょう","kanji":"無料","hint":"free of charge"},
{"niveau":20,"quiz":"non","prononciation":"ない","kanji":"無い","hint":"there is not"},
{"niveau":20,"quiz":"non","prononciation":"ちゃいろ","kanji":"茶色","hint":"brown"},
{"niveau":20,"quiz":"non","prononciation":"あんしんな","kanji":"安心な","hint":"safe "},
{"niveau":20,"quiz":"non","prononciation":"たえる","kanji":"絶える","hint":"to die out"},
{"niveau":20,"quiz":"non","prononciation":"きぜつする","kanji":"気絶する","hint":"to faint"},
{"niveau":20,"quiz":"non","prononciation":"いっつい","kanji":"一対","hint":"a pair"},
{"niveau":20,"quiz":"non","prononciation":"さいこう","kanji":"最高","hint":"the best"},
{"niveau":20,"quiz":"non","prononciation":"さいごに","kanji":"最後に","hint":"lastly"},
{"niveau":20,"quiz":"non","prononciation":"もっとも","kanji":"最も","hint":"most"},
{"niveau":20,"quiz":"non","prononciation":"てつづき","kanji":"手続き","hint":"procedure"},
{"niveau":20,"quiz":"oui","prononciation":"さら","kanji":"皿","hint":"plate; dish"},
{"niveau":20,"quiz":"oui","prononciation":"こえ","kanji":"声","hint":"voice"},
{"niveau":20,"quiz":"oui","prononciation":"おちゃ","kanji":"お茶","hint":"Japanese tea"},
{"niveau":20,"quiz":"oui","prononciation":"ちゃみせ","kanji":"茶店","hint":"teahouse"},
{"niveau":20,"quiz":"oui","prononciation":"とまる","kanji":"止まる","hint":"something stops"},
{"niveau":20,"quiz":"oui","prononciation":"いちまい","kanji":"一枚","hint":"one sheet"},
{"niveau":20,"quiz":"oui","prononciation":"さんりょう","kanji":"三両","hint":"three ryoo"},
{"niveau":20,"quiz":"oui","prononciation":"りょうしん","kanji":"両親","hint":"parents"},
{"niveau":20,"quiz":"oui","prononciation":"むりな","kanji":"無理な","hint":"impossible"},
{"niveau":20,"quiz":"oui","prononciation":"こころ","kanji":"心","hint":"heart; mind"},
{"niveau":20,"quiz":"oui","prononciation":"わらう","kanji":"笑う","hint":"to laugh"},
{"niveau":20,"quiz":"oui","prononciation":"ぜったいに","kanji":"絶対に","hint":"definitively"},
{"niveau":20,"quiz":"oui","prononciation":"いたい","kanji":"痛い","hint":"painful"},
{"niveau":20,"quiz":"oui","prononciation":"さいあく","kanji":"最悪","hint":"the worst"},
{"niveau":20,"quiz":"oui","prononciation":"さいきん","kanji":"最近","hint":"recently"},
{"niveau":20,"quiz":"oui","prononciation":"つづける","kanji":"続ける","hint":"to continue"}]
